cyreal/__init__.py
cyreal/loader.py
cyreal/rl.py
cyreal/sources.py
cyreal/transforms.py
cyreal/datasets/__init__.py
cyreal/datasets/cifar10.py
cyreal/datasets/cifar100.py
cyreal/datasets/daily_min_temperatures.py
cyreal/datasets/dataset_protocol.py
cyreal/datasets/emnist.py
cyreal/datasets/fashion_mnist.py
cyreal/datasets/kmnist.py
cyreal/datasets/mnist.py
cyreal/datasets/mnist_utils.py
cyreal/datasets/sunspots.py
cyreal/datasets/time_utils.py
cyreal/datasets/utils.py
cyreal/tutorials/__init__.py
cyreal/tutorials/buffer_quickstart.py
cyreal/tutorials/disk_stream.py
cyreal/tutorials/host_callback.py
cyreal/tutorials/mnist_quickstart.py
cyreal/tutorials/rl_quickstart.py
cyreal/tutorials/scan_and_jit.py
cyreal-0.1.5.dist-info/METADATA
cyreal-0.1.5.dist-info/WHEEL
cyreal-0.1.5.dist-info/top_level.txt
cyreal-0.1.5.dist-info/RECORD
