Metadata-Version: 2.4
Name: cyreal
Version: 0.1.5
Summary: Jittable data loading utilities for JAX.
Author: 
Classifier: Programming Language :: Python :: 3
Classifier: License :: OSI Approved :: MIT License
Classifier: Operating System :: OS Independent
Requires-Python: >=3.10
Requires-Dist: jax
Requires-Dist: jaxlib
Requires-Dist: numpy
Provides-Extra: dev
Requires-Dist: pytest; extra == "dev"
Requires-Dist: equinox; extra == "dev"
Requires-Dist: optax; extra == "dev"
Requires-Dist: tqdm; extra == "dev"
Requires-Dist: stable-gymnax; extra == "dev"
Dynamic: classifier
Dynamic: description
Dynamic: description-content-type
Dynamic: provides-extra
Dynamic: requires-dist
Dynamic: requires-python
Dynamic: summary
